encodingcom/__init__.py
encodingcom/encoding.py
encodingcom_py3-0.0.5.data/data/README.md
encodingcom_py3-0.0.5.dist-info/DESCRIPTION.rst
encodingcom_py3-0.0.5.dist-info/METADATA
encodingcom_py3-0.0.5.dist-info/metadata.json
encodingcom_py3-0.0.5.dist-info/RECORD
encodingcom_py3-0.0.5.dist-info/top_level.txt
encodingcom_py3-0.0.5.dist-info/WHEEL
