Metadata-Version: 2.0
Name: encodingcom-py3
Version: 0.0.5
Summary: Python 3 wrapper for Encoding.com api
Home-page: https://github.com/studionowinc/encodingcom-py3
Author: Ryan Stubblefield, David Hwu
Author-email: pypi@studionow.com
License: UNKNOWN
Keywords: encoding.com transcoding
Platform: UNKNOWN
Classifier: Development Status :: 3 - Alpha
Classifier: Environment :: Web Environment
Classifier: Natural Language :: English
Classifier: Operating System :: POSIX
Classifier: Programming Language :: Python :: 3
